tv2_bell_automation_framework-1.7.data/scripts/send_command
tv2_bell_automation_framework-1.7.data/scripts/test_runner
tv2_bell_automation_framework-1.7.data/scripts/tv2test-run
tv2_bell_automation_framework-1.7.dist-info/DESCRIPTION.rst
tv2_bell_automation_framework-1.7.dist-info/METADATA
tv2_bell_automation_framework-1.7.dist-info/RECORD
tv2_bell_automation_framework-1.7.dist-info/WHEEL
tv2_bell_automation_framework-1.7.dist-info/metadata.json
tv2_bell_automation_framework-1.7.dist-info/top_level.txt
tv2test/__init__.py
tv2test/config.py
tv2test/constants.py
tv2test/core.py
tv2test/display.py
tv2test/elk_bell.py
tv2test/extend_test_framework.py
tv2test/gst_hacks.py
tv2test/gst_utils.py
tv2test/imgmatch.py
tv2test/imgutils.py
tv2test/merge_audio_video.py
tv2test/motion_detect.py
tv2test/ocr.py
tv2test/send_command.py
tv2test/tc_parser.py
tv2test/test_runner.py
tv2test/text_to_speech.py
tv2test/timeutil.py
tv2test/tv2test-run.py
tv2test/tv2test_run.py
tv2test/voice.py
tv2test/devices/__init__.py
tv2test/devices/core.py
tv2test/devices/itachirblaster.py
tv2test/platforms/__init__.py
tv2test/platforms/mediafirst.py
tv2test/platforms/mediaroom.py
tv2test/platforms/templates/__init__.py
tv2test/platforms/templates/mediafirst/__init__.py
tv2test/platforms/templates/mediafirst/template_guide.jpg
tv2test/platforms/templates/mediafirst/template_netflix_icon.png
tv2test/platforms/templates/mediafirst/template_support_icon.png
tv2test/platforms/templates/mediafirst/template_vod_bell_icon.png
tv2test/platforms/templates/mediafirst/template_youtube_icon.png
tv2test/platforms/templates/mediaroom/__init__.py
tv2test/platforms/templates/mediaroom/template_guide.jpg
tv2test/platforms/templates/mediaroom/template_netflix_icon.png
tv2test/platforms/templates/mediaroom/template_support_icon.png
tv2test/platforms/templates/mediaroom/template_vod_bell_icon.png
tv2test/platforms/templates/mediaroom/template_vod_on_demand.png
tv2test/platforms/templates/mediaroom/template_youtube_icon.png
tv2test/utilities/__init__.py
tv2test/utilities/system_utility.py
